<?xml version="1.0" encoding="UTF-8"?>
<databaseChangeLog
        xmlns="http://www.liquibase.org/xml/ns/dbchangelog"
        xmlns:xsi="http://www.w3.org/2001/XMLSchema-instance"
        xsi:schemaLocation="http://www.liquibase.org/xml/ns/dbchangelog
            http://www.liquibase.org/xml/ns/dbchangelog/dbchangelog-4.1.xsd">

    <changeSet id="2.2" author="Vladimir_Kirdyankin">
        <insert
                tableName="toy">
            <column name="name" value="Панда"/>
            <column name="price" value="5500"/>
            <column name="category_id" value="1"/>
        </insert>
        <insert
                tableName="toy">
            <column name="name" value="Заяц"/>
            <column name="price" value="2500"/>
            <column name="category_id" value="1"/>
        </insert>
        <insert
                tableName="toy">
            <column name="name" value="Шар стеклянный белый"/>
            <column name="price" value="300"/>
            <column name="category_id" value="2"/>
        </insert>
        <insert
                tableName="toy">
            <column name="name" value="Шар стеклянный синий"/>
            <column name="price" value="300"/>
            <column name="category_id" value="2"/>
        </insert>
        <insert
                tableName="toy">
            <column name="name" value="Шар стеклянный красный"/>
            <column name="price" value="300"/>
            <column name="category_id" value="2"/>
        </insert>
    </changeSet>

</databaseChangeLog>